<annotation>
	<folder>okey</folder>
	<filename>947.jpg</filename>
	<path>C:\Users\ntyukaev\Projects\iad\seminar_CV\okey\okey\947.jpg</path>
	<source>
		<database>Unknown</database>
	</source>
	<size>
		<width>1773</width>
		<height>1773</height>
		<depth>3</depth>
	</size>
	<segmented>0</segmented>
	<object>
		<name>price_tag</name>
		<pose>Unspecified</pose>
		<truncated>0</truncated>
		<difficult>0</difficult>
		<bndbox>
			<xmin>95</xmin>
			<ymin>324</ymin>
			<xmax>1526</xmax>
			<ymax>1288</ymax>
		</bndbox>
	</object>
	<object>
		<name>barcode</name>
		<pose>Unspecified</pose>
		<truncated>0</truncated>
		<difficult>0</difficult>
		<bndbox>
			<xmin>229</xmin>
			<ymin>1154</ymin>
			<xmax>638</xmax>
			<ymax>1281</ymax>
		</bndbox>
	</object>
	<object>
		<name>price</name>
		<pose>Unspecified</pose>
		<truncated>0</truncated>
		<difficult>0</difficult>
		<bndbox>
			<xmin>926</xmin>
			<ymin>932</ymin>
			<xmax>1356</xmax>
			<ymax>1141</ymax>
		</bndbox>
	</object>
	<object>
		<name>name</name>
		<pose>Unspecified</pose>
		<truncated>0</truncated>
		<difficult>0</difficult>
		<bndbox>
			<xmin>695</xmin>
			<ymin>427</ymin>
			<xmax>1422</xmax>
			<ymax>717</ymax>
		</bndbox>
	</object>
</annotation>
